test/__init__.py
test/hello.py
test_flask_zqb-0.0.1.dist-info/METADATA
test_flask_zqb-0.0.1.dist-info/WHEEL
test_flask_zqb-0.0.1.dist-info/top_level.txt
test_flask_zqb-0.0.1.dist-info/RECORD
