Metadata-Version: 2.1
Name: test-flask-zqb
Version: 0.0.1
Summary: 测试
Home-page: 
Author: iwen
Author-email: iwen0501@163.com
